{
  "meta": {
    "market": "sz",
    "code": "300087",
    "name": "荃银高科",
    "source_file": "D:\\GitHub\\tdx-strategy-backtest\\data\\day\\sz\\300087.csv",
    "last_date": "2026-01-13T00:00:00"
  },
  "score": {
    "final_score": 80.0,
    "score_A": 0.0,
    "score_B": 0.0,
    "score_C": 80.0
  },
  "signals": [
    {
      "date": "2026-01-13T00:00:00",
      "type": "C_CHAN_BUY",
      "strength": 5,
      "score": 80.0,
      "message": "C策略：缠论买点信号",
      "source": "C",
      "extras": {
        "buy1": false,
        "buy2": true,
        "buy3": false
      }
    }
  ],
  "series": [
    {
      "date": "2025-07-15T00:00:00",
      "open": 9.02,
      "close": 8.88,
      "high": 9.03,
      "low": 8.84,
      "volume": 203270,
      "amount": 181993920.0
    },
    {
      "date": "2025-07-16T00:00:00",
      "open": 8.89,
      "close": 8.96,
      "high": 9.04,
      "low": 8.88,
      "volume": 169912,
      "amount": 153246951.0
    },
    {
      "date": "2025-07-17T00:00:00",
      "open": 8.96,
      "close": 8.98,
      "high": 9.0,
      "low": 8.92,
      "volume": 124054,
      "amount": 111781417.0
    },
    {
      "date": "2025-07-18T00:00:00",
      "open": 8.98,
      "close": 9.02,
      "high": 9.05,
      "low": 8.97,
      "volume": 148462,
      "amount": 134529626.0
    },
    {
      "date": "2025-07-21T00:00:00",
      "open": 8.99,
      "close": 9.1,
      "high": 9.13,
      "low": 8.98,
      "volume": 203148,
      "amount": 185614067.0
    },
    {
      "date": "2025-07-22T00:00:00",
      "open": 9.1,
      "close": 9.11,
      "high": 9.12,
      "low": 9.0,
      "volume": 236142,
      "amount": 213895875.0
    },
    {
      "date": "2025-07-23T00:00:00",
      "open": 9.12,
      "close": 9.08,
      "high": 9.25,
      "low": 9.04,
      "volume": 233593,
      "amount": 213002829.0
    },
    {
      "date": "2025-07-24T00:00:00",
      "open": 9.06,
      "close": 9.38,
      "high": 9.56,
      "low": 9.06,
      "volume": 710858,
      "amount": 662248678.0
    },
    {
      "date": "2025-07-25T00:00:00",
      "open": 9.35,
      "close": 9.2,
      "high": 9.35,
      "low": 9.19,
      "volume": 342191,
      "amount": 315931305.0
    },
    {
      "date": "2025-07-28T00:00:00",
      "open": 9.22,
      "close": 9.16,
      "high": 9.25,
      "low": 9.13,
      "volume": 213067,
      "amount": 195356762.0
    },
    {
      "date": "2025-07-29T00:00:00",
      "open": 9.18,
      "close": 9.11,
      "high": 9.19,
      "low": 9.04,
      "volume": 192874,
      "amount": 175234779.0
    },
    {
      "date": "2025-07-30T00:00:00",
      "open": 9.1,
      "close": 9.29,
      "high": 9.41,
      "low": 9.09,
      "volume": 469645,
      "amount": 434467007.0
    },
    {
      "date": "2025-07-31T00:00:00",
      "open": 9.24,
      "close": 9.08,
      "high": 9.27,
      "low": 9.07,
      "volume": 269869,
      "amount": 246564744.0
    },
    {
      "date": "2025-08-01T00:00:00",
      "open": 9.06,
      "close": 9.1,
      "high": 9.14,
      "low": 9.0,
      "volume": 201068,
      "amount": 182226637.0
    },
    {
      "date": "2025-08-04T00:00:00",
      "open": 9.05,
      "close": 9.1,
      "high": 9.12,
      "low": 9.01,
      "volume": 125153,
      "amount": 113595457.0
    },
    {
      "date": "2025-08-05T00:00:00",
      "open": 9.09,
      "close": 9.17,
      "high": 9.2,
      "low": 9.09,
      "volume": 182384,
      "amount": 166894814.0
    },
    {
      "date": "2025-08-06T00:00:00",
      "open": 9.15,
      "close": 9.13,
      "high": 9.16,
      "low": 9.09,
      "volume": 139260,
      "amount": 126982537.0
    },
    {
      "date": "2025-08-07T00:00:00",
      "open": 9.12,
      "close": 9.27,
      "high": 9.34,
      "low": 9.12,
      "volume": 373874,
      "amount": 345867709.0
    },
    {
      "date": "2025-08-08T00:00:00",
      "open": 9.29,
      "close": 9.26,
      "high": 9.33,
      "low": 9.21,
      "volume": 256051,
      "amount": 236983996.0
    },
    {
      "date": "2025-08-11T00:00:00",
      "open": 9.24,
      "close": 9.3,
      "high": 9.3,
      "low": 9.18,
      "volume": 207539,
      "amount": 192010412.0
    },
    {
      "date": "2025-08-12T00:00:00",
      "open": 9.22,
      "close": 9.22,
      "high": 9.3,
      "low": 9.19,
      "volume": 187845,
      "amount": 173365333.0
    },
    {
      "date": "2025-08-13T00:00:00",
      "open": 9.23,
      "close": 9.23,
      "high": 9.26,
      "low": 9.18,
      "volume": 186079,
      "amount": 171542873.0
    },
    {
      "date": "2025-08-14T00:00:00",
      "open": 9.22,
      "close": 9.05,
      "high": 9.25,
      "low": 9.05,
      "volume": 258082,
      "amount": 236194882.0
    },
    {
      "date": "2025-08-15T00:00:00",
      "open": 9.08,
      "close": 9.19,
      "high": 9.21,
      "low": 9.06,
      "volume": 196849,
      "amount": 180078082.0
    },
    {
      "date": "2025-08-18T00:00:00",
      "open": 9.25,
      "close": 9.33,
      "high": 9.35,
      "low": 9.21,
      "volume": 368769,
      "amount": 342771989.0
    },
    {
      "date": "2025-08-19T00:00:00",
      "open": 9.37,
      "close": 9.29,
      "high": 9.41,
      "low": 9.25,
      "volume": 219401,
      "amount": 204063741.0
    },
    {
      "date": "2025-08-20T00:00:00",
      "open": 9.28,
      "close": 9.35,
      "high": 9.41,
      "low": 9.22,
      "volume": 276534,
      "amount": 257524298.0
    },
    {
      "date": "2025-08-21T00:00:00",
      "open": 9.33,
      "close": 9.42,
      "high": 9.6,
      "low": 9.3,
      "volume": 435208,
      "amount": 411057170.0
    },
    {
      "date": "2025-08-22T00:00:00",
      "open": 9.39,
      "close": 9.41,
      "high": 9.42,
      "low": 9.28,
      "volume": 282150,
      "amount": 263640836.0
    },
    {
      "date": "2025-08-25T00:00:00",
      "open": 9.45,
      "close": 9.72,
      "high": 9.83,
      "low": 9.4,
      "volume": 691562,
      "amount": 667101036.0
    },
    {
      "date": "2025-08-26T00:00:00",
      "open": 9.73,
      "close": 9.66,
      "high": 9.83,
      "low": 9.63,
      "volume": 425610,
      "amount": 413547817.0
    },
    {
      "date": "2025-08-27T00:00:00",
      "open": 9.63,
      "close": 9.8,
      "high": 9.94,
      "low": 9.57,
      "volume": 632752,
      "amount": 614933624.0
    },
    {
      "date": "2025-08-28T00:00:00",
      "open": 9.61,
      "close": 9.39,
      "high": 9.63,
      "low": 9.23,
      "volume": 597268,
      "amount": 562169105.0
    },
    {
      "date": "2025-08-29T00:00:00",
      "open": 9.35,
      "close": 9.36,
      "high": 9.58,
      "low": 9.29,
      "volume": 327661,
      "amount": 308923185.0
    },
    {
      "date": "2025-09-01T00:00:00",
      "open": 9.31,
      "close": 9.33,
      "high": 9.38,
      "low": 9.19,
      "volume": 244046,
      "amount": 226644759.0
    },
    {
      "date": "2025-09-02T00:00:00",
      "open": 9.3,
      "close": 9.33,
      "high": 9.57,
      "low": 9.24,
      "volume": 375373,
      "amount": 352720877.0
    },
    {
      "date": "2025-09-03T00:00:00",
      "open": 9.33,
      "close": 8.98,
      "high": 9.43,
      "low": 8.88,
      "volume": 367054,
      "amount": 335998756.0
    },
    {
      "date": "2025-09-04T00:00:00",
      "open": 8.94,
      "close": 9.0,
      "high": 9.09,
      "low": 8.9,
      "volume": 211181,
      "amount": 189927427.0
    },
    {
      "date": "2025-09-05T00:00:00",
      "open": 9.0,
      "close": 9.03,
      "high": 9.03,
      "low": 8.85,
      "volume": 216835,
      "amount": 194483038.0
    },
    {
      "date": "2025-09-08T00:00:00",
      "open": 9.03,
      "close": 9.17,
      "high": 9.22,
      "low": 9.01,
      "volume": 225106,
      "amount": 205792639.0
    },
    {
      "date": "2025-09-09T00:00:00",
      "open": 9.16,
      "close": 9.06,
      "high": 9.2,
      "low": 9.0,
      "volume": 154238,
      "amount": 139973547.0
    },
    {
      "date": "2025-09-10T00:00:00",
      "open": 9.05,
      "close": 9.06,
      "high": 9.08,
      "low": 9.01,
      "volume": 123260,
      "amount": 111467931.0
    },
    {
      "date": "2025-09-11T00:00:00",
      "open": 9.06,
      "close": 9.13,
      "high": 9.16,
      "low": 9.02,
      "volume": 211779,
      "amount": 192216114.0
    },
    {
      "date": "2025-09-12T00:00:00",
      "open": 9.12,
      "close": 9.11,
      "high": 9.2,
      "low": 9.08,
      "volume": 171596,
      "amount": 156663516.0
    },
    {
      "date": "2025-09-15T00:00:00",
      "open": 9.12,
      "close": 9.23,
      "high": 9.38,
      "low": 9.1,
      "volume": 222948,
      "amount": 205936280.0
    },
    {
      "date": "2025-09-16T00:00:00",
      "open": 9.16,
      "close": 9.18,
      "high": 9.18,
      "low": 9.08,
      "volume": 177653,
      "amount": 162054051.0
    },
    {
      "date": "2025-09-17T00:00:00",
      "open": 9.15,
      "close": 9.13,
      "high": 9.17,
      "low": 9.09,
      "volume": 134388,
      "amount": 122561079.0
    },
    {
      "date": "2025-09-18T00:00:00",
      "open": 9.11,
      "close": 9.03,
      "high": 9.22,
      "low": 8.98,
      "volume": 264476,
      "amount": 240248562.0
    },
    {
      "date": "2025-09-19T00:00:00",
      "open": 9.0,
      "close": 9.02,
      "high": 9.06,
      "low": 8.96,
      "volume": 116197,
      "amount": 104718699.0
    },
    {
      "date": "2025-09-22T00:00:00",
      "open": 9.05,
      "close": 9.09,
      "high": 9.22,
      "low": 8.99,
      "volume": 203467,
      "amount": 185329924.0
    },
    {
      "date": "2025-09-23T00:00:00",
      "open": 9.09,
      "close": 9.22,
      "high": 9.29,
      "low": 8.96,
      "volume": 313442,
      "amount": 286654360.0
    },
    {
      "date": "2025-09-24T00:00:00",
      "open": 9.16,
      "close": 9.35,
      "high": 9.38,
      "low": 9.16,
      "volume": 302759,
      "amount": 281093130.0
    },
    {
      "date": "2025-09-25T00:00:00",
      "open": 9.35,
      "close": 9.22,
      "high": 9.35,
      "low": 9.18,
      "volume": 182840,
      "amount": 168981610.0
    },
    {
      "date": "2025-09-26T00:00:00",
      "open": 9.22,
      "close": 9.14,
      "high": 9.38,
      "low": 9.13,
      "volume": 209405,
      "amount": 193465732.0
    },
    {
      "date": "2025-09-29T00:00:00",
      "open": 9.13,
      "close": 9.1,
      "high": 9.14,
      "low": 9.02,
      "volume": 154369,
      "amount": 140017669.0
    },
    {
      "date": "2025-09-30T00:00:00",
      "open": 9.13,
      "close": 9.17,
      "high": 9.19,
      "low": 9.05,
      "volume": 115158,
      "amount": 105046037.0
    },
    {
      "date": "2025-10-09T00:00:00",
      "open": 9.11,
      "close": 9.17,
      "high": 9.2,
      "low": 9.03,
      "volume": 146621,
      "amount": 133559562.0
    },
    {
      "date": "2025-10-10T00:00:00",
      "open": 9.19,
      "close": 9.22,
      "high": 9.28,
      "low": 9.17,
      "volume": 212232,
      "amount": 195826987.0
    },
    {
      "date": "2025-10-13T00:00:00",
      "open": 9.51,
      "close": 9.26,
      "high": 9.68,
      "low": 9.24,
      "volume": 547251,
      "amount": 515662537.0
    },
    {
      "date": "2025-10-14T00:00:00",
      "open": 9.15,
      "close": 9.29,
      "high": 9.4,
      "low": 9.14,
      "volume": 419392,
      "amount": 388078877.0
    },
    {
      "date": "2025-10-15T00:00:00",
      "open": 9.22,
      "close": 9.14,
      "high": 9.23,
      "low": 9.03,
      "volume": 261334,
      "amount": 238632424.0
    },
    {
      "date": "2025-10-16T00:00:00",
      "open": 9.17,
      "close": 9.1,
      "high": 9.19,
      "low": 9.08,
      "volume": 173998,
      "amount": 158796115.0
    },
    {
      "date": "2025-10-17T00:00:00",
      "open": 9.07,
      "close": 9.01,
      "high": 9.13,
      "low": 9.0,
      "volume": 224097,
      "amount": 202968195.0
    },
    {
      "date": "2025-10-20T00:00:00",
      "open": 9.02,
      "close": 9.03,
      "high": 9.04,
      "low": 8.94,
      "volume": 120508,
      "amount": 108518292.0
    },
    {
      "date": "2025-10-21T00:00:00",
      "open": 9.02,
      "close": 9.05,
      "high": 9.06,
      "low": 9.0,
      "volume": 105957,
      "amount": 95720632.0
    },
    {
      "date": "2025-10-22T00:00:00",
      "open": 9.03,
      "close": 8.96,
      "high": 9.06,
      "low": 8.92,
      "volume": 181043,
      "amount": 162717858.0
    },
    {
      "date": "2025-10-23T00:00:00",
      "open": 8.97,
      "close": 8.97,
      "high": 9.01,
      "low": 8.92,
      "volume": 101653,
      "amount": 91131139.0
    },
    {
      "date": "2025-10-24T00:00:00",
      "open": 8.97,
      "close": 9.04,
      "high": 9.07,
      "low": 8.94,
      "volume": 134656,
      "amount": 121384108.0
    },
    {
      "date": "2025-10-27T00:00:00",
      "open": 8.98,
      "close": 9.04,
      "high": 9.05,
      "low": 8.97,
      "volume": 129281,
      "amount": 116528747.0
    },
    {
      "date": "2025-10-28T00:00:00",
      "open": 9.02,
      "close": 9.05,
      "high": 9.06,
      "low": 8.99,
      "volume": 111229,
      "amount": 100306741.0
    },
    {
      "date": "2025-10-29T00:00:00",
      "open": 9.05,
      "close": 8.99,
      "high": 9.05,
      "low": 8.98,
      "volume": 127526,
      "amount": 114799087.0
    },
    {
      "date": "2025-10-30T00:00:00",
      "open": 8.89,
      "close": 8.87,
      "high": 9.02,
      "low": 8.76,
      "volume": 228505,
      "amount": 202536903.0
    },
    {
      "date": "2025-10-31T00:00:00",
      "open": 8.81,
      "close": 8.85,
      "high": 8.9,
      "low": 8.78,
      "volume": 103147,
      "amount": 91342424.0
    },
    {
      "date": "2025-11-03T00:00:00",
      "open": 8.85,
      "close": 8.9,
      "high": 8.93,
      "low": 8.83,
      "volume": 97341,
      "amount": 86426966.0
    },
    {
      "date": "2025-11-04T00:00:00",
      "open": 8.89,
      "close": 8.86,
      "high": 8.95,
      "low": 8.82,
      "volume": 104023,
      "amount": 92323723.0
    },
    {
      "date": "2025-11-05T00:00:00",
      "open": 8.82,
      "close": 8.93,
      "high": 9.0,
      "low": 8.81,
      "volume": 125613,
      "amount": 111979117.0
    },
    {
      "date": "2025-11-06T00:00:00",
      "open": 8.93,
      "close": 8.86,
      "high": 8.93,
      "low": 8.84,
      "volume": 107164,
      "amount": 95045438.0
    },
    {
      "date": "2025-11-07T00:00:00",
      "open": 8.87,
      "close": 8.83,
      "high": 8.91,
      "low": 8.83,
      "volume": 112760,
      "amount": 99959376.0
    },
    {
      "date": "2025-11-10T00:00:00",
      "open": 8.82,
      "close": 8.88,
      "high": 8.9,
      "low": 8.78,
      "volume": 115875,
      "amount": 102542518.0
    },
    {
      "date": "2025-11-11T00:00:00",
      "open": 8.89,
      "close": 9.22,
      "high": 9.27,
      "low": 8.83,
      "volume": 451727,
      "amount": 412073916.0
    },
    {
      "date": "2025-11-12T00:00:00",
      "open": 9.22,
      "close": 9.28,
      "high": 9.35,
      "low": 9.2,
      "volume": 283081,
      "amount": 262575129.0
    },
    {
      "date": "2025-11-13T00:00:00",
      "open": 9.28,
      "close": 9.23,
      "high": 9.31,
      "low": 9.16,
      "volume": 167249,
      "amount": 154211086.0
    },
    {
      "date": "2025-11-14T00:00:00",
      "open": 9.23,
      "close": 9.27,
      "high": 9.49,
      "low": 9.23,
      "volume": 249971,
      "amount": 233336156.0
    },
    {
      "date": "2025-11-17T00:00:00",
      "open": 9.31,
      "close": 9.52,
      "high": 9.56,
      "low": 9.25,
      "volume": 388222,
      "amount": 365869874.0
    },
    {
      "date": "2025-11-18T00:00:00",
      "open": 9.5,
      "close": 9.98,
      "high": 10.19,
      "low": 9.48,
      "volume": 818374,
      "amount": 808932180.0
    },
    {
      "date": "2025-11-19T00:00:00",
      "open": 10.09,
      "close": 10.01,
      "high": 10.13,
      "low": 9.77,
      "volume": 494510,
      "amount": 491569153.0
    },
    {
      "date": "2025-11-20T00:00:00",
      "open": 10.08,
      "close": 10.16,
      "high": 10.55,
      "low": 10.06,
      "volume": 570228,
      "amount": 587576408.0
    },
    {
      "date": "2025-11-21T00:00:00",
      "open": 11.68,
      "close": 11.81,
      "high": 12.19,
      "low": 11.65,
      "volume": 1925771,
      "amount": 2306824410.0
    },
    {
      "date": "2025-11-24T00:00:00",
      "open": 11.77,
      "close": 11.44,
      "high": 11.96,
      "low": 11.44,
      "volume": 1399094,
      "amount": 1619018439.0
    },
    {
      "date": "2025-11-25T00:00:00",
      "open": 11.57,
      "close": 11.35,
      "high": 11.64,
      "low": 11.25,
      "volume": 1055348,
      "amount": 1205210432.0
    },
    {
      "date": "2025-11-26T00:00:00",
      "open": 11.39,
      "close": 11.42,
      "high": 11.5,
      "low": 11.3,
      "volume": 669730,
      "amount": 763018681.0
    },
    {
      "date": "2025-11-27T00:00:00",
      "open": 11.44,
      "close": 11.42,
      "high": 11.64,
      "low": 11.32,
      "volume": 681017,
      "amount": 780625021.0
    },
    {
      "date": "2025-11-28T00:00:00",
      "open": 11.4,
      "close": 11.5,
      "high": 11.5,
      "low": 11.38,
      "volume": 423668,
      "amount": 484325610.0
    },
    {
      "date": "2025-12-01T00:00:00",
      "open": 11.49,
      "close": 11.53,
      "high": 11.53,
      "low": 11.42,
      "volume": 386185,
      "amount": 442725120.0
    },
    {
      "date": "2025-12-02T00:00:00",
      "open": 11.49,
      "close": 11.5,
      "high": 11.59,
      "low": 11.47,
      "volume": 347853,
      "amount": 401098562.0
    },
    {
      "date": "2025-12-03T00:00:00",
      "open": 11.55,
      "close": 11.59,
      "high": 11.64,
      "low": 11.48,
      "volume": 460719,
      "amount": 533537558.0
    },
    {
      "date": "2025-12-04T00:00:00",
      "open": 11.6,
      "close": 11.49,
      "high": 11.63,
      "low": 11.46,
      "volume": 435113,
      "amount": 501591810.0
    },
    {
      "date": "2025-12-05T00:00:00",
      "open": 11.5,
      "close": 11.53,
      "high": 11.59,
      "low": 11.48,
      "volume": 344397,
      "amount": 397309669.0
    },
    {
      "date": "2025-12-08T00:00:00",
      "open": 11.52,
      "close": 11.5,
      "high": 11.54,
      "low": 11.47,
      "volume": 333354,
      "amount": 383124908.0
    },
    {
      "date": "2025-12-09T00:00:00",
      "open": 11.49,
      "close": 11.46,
      "high": 11.52,
      "low": 11.44,
      "volume": 277642,
      "amount": 318500817.0
    },
    {
      "date": "2025-12-10T00:00:00",
      "open": 11.47,
      "close": 11.51,
      "high": 11.52,
      "low": 11.43,
      "volume": 348942,
      "amount": 400632944.0
    },
    {
      "date": "2025-12-11T00:00:00",
      "open": 11.48,
      "close": 11.44,
      "high": 11.51,
      "low": 11.43,
      "volume": 273257,
      "amount": 313251682.0
    },
    {
      "date": "2025-12-12T00:00:00",
      "open": 11.44,
      "close": 11.37,
      "high": 11.46,
      "low": 11.36,
      "volume": 374293,
      "amount": 426885101.0
    },
    {
      "date": "2025-12-15T00:00:00",
      "open": 11.37,
      "close": 11.34,
      "high": 11.39,
      "low": 11.33,
      "volume": 240099,
      "amount": 272642688.0
    },
    {
      "date": "2025-12-16T00:00:00",
      "open": 11.33,
      "close": 11.31,
      "high": 11.38,
      "low": 11.29,
      "volume": 281817,
      "amount": 319083902.0
    },
    {
      "date": "2025-12-17T00:00:00",
      "open": 11.32,
      "close": 11.31,
      "high": 11.34,
      "low": 11.26,
      "volume": 218824,
      "amount": 247053444.0
    },
    {
      "date": "2025-12-18T00:00:00",
      "open": 11.32,
      "close": 11.36,
      "high": 11.44,
      "low": 11.31,
      "volume": 238534,
      "amount": 271652157.0
    },
    {
      "date": "2025-12-19T00:00:00",
      "open": 11.36,
      "close": 11.41,
      "high": 11.42,
      "low": 11.35,
      "volume": 164535,
      "amount": 187494701.0
    },
    {
      "date": "2025-12-22T00:00:00",
      "open": 11.41,
      "close": 11.45,
      "high": 11.47,
      "low": 11.38,
      "volume": 238162,
      "amount": 272175925.0
    },
    {
      "date": "2025-12-23T00:00:00",
      "open": 11.43,
      "close": 11.47,
      "high": 11.58,
      "low": 11.43,
      "volume": 410860,
      "amount": 473190790.0
    },
    {
      "date": "2025-12-24T00:00:00",
      "open": 11.49,
      "close": 11.58,
      "high": 11.6,
      "low": 11.45,
      "volume": 350418,
      "amount": 405242210.0
    },
    {
      "date": "2025-12-25T00:00:00",
      "open": 11.59,
      "close": 11.57,
      "high": 11.62,
      "low": 11.55,
      "volume": 191840,
      "amount": 222141505.0
    },
    {
      "date": "2025-12-26T00:00:00",
      "open": 11.57,
      "close": 11.53,
      "high": 11.59,
      "low": 11.51,
      "volume": 239688,
      "amount": 276615605.0
    },
    {
      "date": "2025-12-29T00:00:00",
      "open": 11.55,
      "close": 11.62,
      "high": 11.63,
      "low": 11.52,
      "volume": 264285,
      "amount": 306061581.0
    },
    {
      "date": "2025-12-30T00:00:00",
      "open": 11.6,
      "close": 11.54,
      "high": 11.68,
      "low": 11.52,
      "volume": 398977,
      "amount": 461973409.0
    },
    {
      "date": "2025-12-31T00:00:00",
      "open": 11.55,
      "close": 11.68,
      "high": 11.7,
      "low": 11.54,
      "volume": 513511,
      "amount": 597834015.0
    },
    {
      "date": "2026-01-05T00:00:00",
      "open": 11.71,
      "close": 11.69,
      "high": 11.75,
      "low": 11.58,
      "volume": 637972,
      "amount": 745401072.0
    },
    {
      "date": "2026-01-09T00:00:00",
      "open": 10.75,
      "close": 10.76,
      "high": 11.02,
      "low": 10.62,
      "volume": 946076,
      "amount": 1024502950.0
    },
    {
      "date": "2026-01-12T00:00:00",
      "open": 10.78,
      "close": 10.46,
      "high": 10.78,
      "low": 10.35,
      "volume": 565930,
      "amount": 592050944.0
    },
    {
      "date": "2026-01-13T00:00:00",
      "open": 10.48,
      "close": 10.55,
      "high": 10.75,
      "low": 10.42,
      "volume": 214796,
      "amount": 227366414.11
    }
  ]
}